kpnboxapi/__init__.py
kpnboxapi/client.py
kpnboxapi/exceptions.py
kpnboxapi-0.1.3.dist-info/licenses/LICENSE
kpnboxapi-0.1.3.dist-info/METADATA
kpnboxapi-0.1.3.dist-info/WHEEL
kpnboxapi-0.1.3.dist-info/top_level.txt
kpnboxapi-0.1.3.dist-info/RECORD
