Metadata-Version: 2.4
Name: kpnboxapi
Version: 0.1.3
Summary: Python library for interacting with KPN Box modem/router
Author-email: ssl <git@elyesa.nl>
License: MIT
Project-URL: Homepage, https://github.com/ssl/KPNBoxAPI
Project-URL: Repository, https://github.com/ssl/KPNBoxAPI.git
Project-URL: Issues, https://github.com/ssl/KPNBoxAPI/issues
Keywords: kpn,modem,router,api,networking,home automation
Classifier: Development Status :: 4 - Beta
Classifier: Intended Audience :: Developers
Classifier: License :: OSI Approved :: MIT License
Classifier: Operating System :: OS Independent
Classifier: Programming Language :: Python :: 3
Classifier: Programming Language :: Python :: 3.8
Classifier: Programming Language :: Python :: 3.9
Classifier: Programming Language :: Python :: 3.10
Classifier: Programming Language :: Python :: 3.11
Classifier: Programming Language :: Python :: 3.12
Classifier: Topic :: Software Development :: Libraries :: Python Modules
Classifier: Topic :: System :: Networking
Requires-Python: >=3.8
License-File: LICENSE
Requires-Dist: requests>=2.25.0
Provides-Extra: dev
Requires-Dist: flake8>=5.0.0; extra == "dev"
Requires-Dist: black>=22.0.0; extra == "dev"
Requires-Dist: mypy>=1.0.0; extra == "dev"
Requires-Dist: build>=0.10.0; extra == "dev"
Requires-Dist: twine>=4.0.0; extra == "dev"
Dynamic: license-file
